pipelineviewer/__init__.py
pipelineviewer/ariane.py
pipelineviewer/base.py
pipelineviewer/boom.py
pipelineviewer/ctf.py
pipelineviewer/ibex.py
pipelineviewer/main.py
pipelineviewer/swerv.py
pipelineviewer/version.py
pipelineviewer-0.3.7.dist-info/METADATA
pipelineviewer-0.3.7.dist-info/WHEEL
pipelineviewer-0.3.7.dist-info/entry_points.txt
pipelineviewer-0.3.7.dist-info/top_level.txt
pipelineviewer-0.3.7.dist-info/RECORD
