Metadata-Version: 2.1
Name: pipelineviewer
Version: 0.3.7
Summary: CPU Pipeline Viewer
Home-page: https://github.com/wallento/pipeline-viewer
Author: Stefan Wallentowitz
Author-email: stefan@wallentowitz.de
Keywords: cpu pipeline viewer
Classifier: Development Status :: 3 - Alpha
Classifier: License :: OSI Approved :: MIT License
Classifier: Programming Language :: Python :: 3
Classifier: Programming Language :: Python :: 3.4
Classifier: Programming Language :: Python :: 3.5
Classifier: Programming Language :: Python :: 3.6
Requires-Dist: attrdict3
Requires-Dist: colorama
Requires-Dist: pygments
Requires-Dist: riscv-model (>=0.6.6)
